black_body/__init__.py
black_body/constants.py
black_body/energy.py
black_body/version.py
black_body-1.1.0.dist-info/AUTHORS.rst
black_body-1.1.0.dist-info/LICENSE
black_body-1.1.0.dist-info/METADATA
black_body-1.1.0.dist-info/WHEEL
black_body-1.1.0.dist-info/top_level.txt
black_body-1.1.0.dist-info/RECORD
