Metadata-Version: 2.1
Name: black_body
Version: 1.1.0
Summary: Set of formalisms around black bodies
Home-page: https://gitlab.com/revesansparole/black_body
Author: revesansparole
Author-email: revesansparole@gmail.com
License: cc_by_nc
Classifier: Development Status :: 2 - Pre-Alpha
Classifier: Intended Audience :: Developers
Classifier: License :: OSI Approved :: BSD License
Classifier: Natural Language :: English
Classifier: Programming Language :: Python
Classifier: Programming Language :: Python :: 3
Classifier: Programming Language :: Python :: 3 :: Only
Classifier: Programming Language :: Python :: 3.10
Classifier: Programming Language :: Python :: 3.11
Classifier: Programming Language :: Python :: 3.9
License-File: LICENSE
License-File: AUTHORS.rst
